MathLang/Interface/CLI/__init__.py
MathLang_CLI-2021.0.dist-info/LICENSE
MathLang_CLI-2021.0.dist-info/METADATA
MathLang_CLI-2021.0.dist-info/WHEEL
MathLang_CLI-2021.0.dist-info/top_level.txt
MathLang_CLI-2021.0.dist-info/RECORD
