Metadata-Version: 2.1
Name: MathLang-CLI
Version: 2021.0
Summary: MathLang-CLI is an extension for MathLang to support CLI application.
Home-page: https://github.com/GreaterGoodCorp/MathLang
Author: GreaterGoodCorp
Author-email: binhnt.mdev@gmail.com
License: MIT License
Project-URL: Bug Tracker, https://github.com/GreaterGoodCorp/MathLang/issues
Platform: UNKNOWN
Classifier: Development Status :: 3 - Alpha
Classifier: Intended Audience :: Developers
Classifier: Intended Audience :: End Users/Desktop
Classifier: License :: OSI Approved :: MIT License
Classifier: Natural Language :: English
Classifier: Operating System :: OS Independent
Classifier: Programming Language :: Python :: 3.6
Classifier: Programming Language :: Python :: 3.7
Classifier: Programming Language :: Python :: 3.8
Classifier: Programming Language :: Python :: 3.9
Classifier: Topic :: Education
Classifier: Topic :: Utilities
Requires-Python: >=3.6
Requires-Dist: MathLang (~=2021.0)
Requires-Dist: click (~=8.0.1)
